<?xml version="1.0" ?>
<tv generator-info-name="Auto EPG Smart Sports">
  <programme start="20260608110000 +0700" stop="20260608130000 +0700" channel="nbatvspectrumsportsnetrosecitysportsnetnbatvcanada">
    <title lang="id">Portland Fire @ Los Angeles Sparks</title>
    <desc lang="id">[Akan Tayang] Disiarkan di: NBA TV, Spectrum SportsNet, Rose City SportsNet, NBA TV Canada</desc>
    <category lang="id">Olahraga</category>
  </programme>
  <programme start="20260608100000 +0700" stop="20260608120000 +0700" channel="fubosportsespnunlimitedespn">
    <title lang="id">Kansas @ Oklahoma</title>
    <desc lang="id">[Akan Tayang] Disiarkan di: Fubo Sports, ESPN Unlimited, ESPN</desc>
    <category lang="id">Olahraga</category>
  </programme>
  <programme start="20260608100500 +0700" stop="20260608120500 +0700" channel="flohockey">
    <title lang="id">Toronto Marlies @ Wilkes-Barre/Scranton</title>
    <desc lang="id">[Akan Tayang] Disiarkan di: FloHockey</desc>
    <category lang="id">Olahraga</category>
  </programme>
  <programme start="20260608110000 +0700" stop="20260608130000 +0700" channel="tln">
    <title lang="id">Colombia Jordan ESPN Unlimited Fanatiz ESPN Deportes In Demand 1</title>
    <desc lang="id">[Akan Tayang] Disiarkan di: TLN</desc>
    <category lang="id">Olahraga</category>
  </programme>
  <programme start="20260608100000 +0700" stop="20260608120000 +0700" channel="fubosportsfoxfox4ktsn+">
    <title lang="id">Louisville Kings @ St. Louis Battlehawks</title>
    <desc lang="id">[Akan Tayang] Disiarkan di: Fubo Sports, FOX, FOX 4K, TSN+</desc>
    <category lang="id">Olahraga</category>
  </programme>
  <programme start="20260608103000 +0700" stop="20260608123000 +0700" channel="rds2">
    <title lang="id">U.S. Women's Open Final Round</title>
    <desc lang="id">[Akan Tayang] Disiarkan di: RDS 2</desc>
    <category lang="id">Olahraga</category>
  </programme>
  <programme start="20260608093000 +0700" stop="20260608113000 +0700" channel="fubosportsfoxsports1revtv">
    <title lang="id">World Wide Technology Raceway Race</title>
    <desc lang="id">[Akan Tayang] Disiarkan di: Fubo Sports, FOX Sports 1, REV TV</desc>
    <category lang="id">Olahraga</category>
  </programme>
  <programme start="20260608110000 +0700" stop="20260608130000 +0700" channel="floracing">
    <title lang="id">Silver Crown at World Wide Technology Raceway</title>
    <desc lang="id">[Akan Tayang] Disiarkan di: FloRacing</desc>
    <category lang="id">Olahraga</category>
  </programme>
  <programme start="20260608093000 +0700" stop="20260608113000 +0700" channel="fubosportsfoxsports2">
    <title lang="id">America's Day at the Races</title>
    <desc lang="id">[Akan Tayang] Disiarkan di: Fubo Sports, FOX Sports 2</desc>
    <category lang="id">Olahraga</category>
  </programme>
  <programme start="20260608100000 +0700" stop="20260608120000 +0700" channel="wsn">
    <title lang="id">Bay Breakers @ Boston Banshees</title>
    <desc lang="id">[Akan Tayang] Disiarkan di: WSN</desc>
    <category lang="id">Olahraga</category>
  </programme>
  <programme start="20260608100000 +0700" stop="20260608120000 +0700" channel="tvasports">
    <title lang="id">Japan @ Canada</title>
    <desc lang="id">[Akan Tayang] Disiarkan di: TVA Sports</desc>
    <category lang="id">Olahraga</category>
  </programme>
</tv>
